anylabeling/__init__.py
anylabeling/app.py
anylabeling/app_info.py
anylabeling/config.py
anylabeling/utils.py
anylabeling/configs/__init__.py
anylabeling/configs/anylabeling_config.yaml
anylabeling/configs/auto_labeling/__init__.py
anylabeling/configs/auto_labeling/models.yaml
anylabeling/resources/__init__.py
anylabeling/resources/resources.py
anylabeling/services/__init__.py
anylabeling/services/auto_labeling/__init__.py
anylabeling/services/auto_labeling/lru_cache.py
anylabeling/services/auto_labeling/model.py
anylabeling/services/auto_labeling/model_manager.py
anylabeling/services/auto_labeling/sam2_onnx.py
anylabeling/services/auto_labeling/sam_onnx.py
anylabeling/services/auto_labeling/segment_anything.py
anylabeling/services/auto_labeling/types.py
anylabeling/services/auto_labeling/yolov5.py
anylabeling/services/auto_labeling/yolov8.py
anylabeling/styles/__init__.py
anylabeling/styles/theme.py
anylabeling/views/__init__.py
anylabeling/views/mainwindow.py
anylabeling/views/common/__init__.py
anylabeling/views/common/toaster.py
anylabeling/views/labeling/__init__.py
anylabeling/views/labeling/label_file.py
anylabeling/views/labeling/label_widget.py
anylabeling/views/labeling/label_wrapper.py
anylabeling/views/labeling/logger.py
anylabeling/views/labeling/shape.py
anylabeling/views/labeling/testing.py
anylabeling/views/labeling/utils/__init__.py
anylabeling/views/labeling/utils/_io.py
anylabeling/views/labeling/utils/export_formats.py
anylabeling/views/labeling/utils/export_worker.py
anylabeling/views/labeling/utils/image.py
anylabeling/views/labeling/utils/opencv.py
anylabeling/views/labeling/utils/qt.py
anylabeling/views/labeling/utils/shape.py
anylabeling/views/labeling/widgets/__init__.py
anylabeling/views/labeling/widgets/brightness_contrast_dialog.py
anylabeling/views/labeling/widgets/canvas.py
anylabeling/views/labeling/widgets/color_dialog.py
anylabeling/views/labeling/widgets/escapable_qlist_widget.py
anylabeling/views/labeling/widgets/export_dialog.py
anylabeling_gpu-0.4.30.dist-info/licenses/LICENSE
anylabeling_gpu-0.4.30.dist-info/METADATA
anylabeling_gpu-0.4.30.dist-info/WHEEL
anylabeling_gpu-0.4.30.dist-info/entry_points.txt
anylabeling_gpu-0.4.30.dist-info/top_level.txt
anylabeling_gpu-0.4.30.dist-info/RECORD
